Metadata-Version: 2.1
Name: datasette-enrichments-re2
Version: 0.1
Summary: Enrich data using regular expressions
Author: Simon Willison
License: Apache-2.0
Project-URL: Homepage, https://github.com/datasette/datasette-enrichments-re2
Project-URL: Changelog, https://github.com/datasette/datasette-enrichments-re2/releases
Project-URL: Issues, https://github.com/datasette/datasette-enrichments-re2/issues
Project-URL: CI, https://github.com/datasette/datasette-enrichments-re2/actions
Classifier: Framework :: Datasette
Classifier: License :: OSI Approved :: Apache Software License
Requires-Python: >=3.8
License-File: LICENSE
Requires-Dist: datasette
Requires-Dist: datasette-enrichments >=0.2
Requires-Dist: google-re2
Requires-Dist: sqlite-utils
Provides-Extra: test
Requires-Dist: pytest ; extra == 'test'
Requires-Dist: pytest-asyncio ; extra == 'test'
